also_anomaly_detector/AlsoAnomalyDetector.py
also_anomaly_detector/__init__.py
also_anomaly_detector-0.0.2.dist-info/AUTHORS.rst
also_anomaly_detector-0.0.2.dist-info/LICENSE.txt
also_anomaly_detector-0.0.2.dist-info/METADATA
also_anomaly_detector-0.0.2.dist-info/WHEEL
also_anomaly_detector-0.0.2.dist-info/top_level.txt
also_anomaly_detector-0.0.2.dist-info/RECORD
